{
	"formats" : 
	[
		{
			"at" : "M",
			"d" : 209,
			"hd" : false,
			"imageUri" : "https://brightcove.hs.llnwd.net/v1/unsecured/media/3965454539001/201506/304/3965454539001_4300086591001_V-for-vandetta-no-text.jpg?pubId=3965454539001",
			"oigid" : -1905684972,
			"provider" : "TasteMade",
			"streamLink" : "http://9bnjl7mn.skychnl.net/9BNJL7MN/E7KL0QKCURSJ/m3u8/E7KL0QKCURSJ.m3u8"
		}
	],
	"seasonuuid" : "",
	"seriesuuid" : "",
	"sy" : "V for Vendetta inspires a special take on “Eggie in a basket”. Deliciously crisp crust with a creamy brie and perfectly cooked egg center. Tangy wild blueberries on the bottom and a little added sweetness of maple syrup drizzled over top.",
	"t" : "1. V for Vendetta | Inspired Recipe for Eggie in a Basket",
	"uuid" : "Episode4298171419001110036"
}