{
	"formats" : 
	[
		{
			"at" : "M",
			"d" : 71,
			"hd" : false,
			"imageUri" : "https://brightcove.hs.llnwd.net/v1/unsecured/media/3965454539001/201504/3689/3965454539001_4158522378001_7.jpg?pubId=3965454539001",
			"oigid" : -1028231411,
			"provider" : "TasteMade",
			"streamLink" : "http://9bnjl7mn.skychnl.net/9BNJL7MN/4NYAYNK3MWVF/m3u8/4NYAYNK3MWVF.m3u8"
		}
	],
	"seasonuuid" : "",
	"seriesuuid" : "",
	"sy" : "Serving up cake balls, macarons, mini pies, cupcakes and more in City Center, Sweet is a true dessert lovers’ happy place. After you try their Key lime mini pie, you’re sure to be sweet on Sweet.",
	"t" : "8. Sweet",
	"uuid" : "Episode4110117742001110797"
}