{
	"formats" : 
	[
		{
			"at" : "M",
			"d" : 196,
			"hd" : false,
			"imageUri" : "https://brightcove.hs.llnwd.net/v1/unsecured/media/3965454539001/201501/1565/3965454539001_4003492696001_nachos.jpg?pubId=3965454539001",
			"oigid" : 842235760,
			"provider" : "TasteMade",
			"streamLink" : "http://9bnjl7mn.skychnl.net/9BNJL7MN/ES9M9VEY8EPS/m3u8/ES9M9VEY8EPS.m3u8"
		}
	],
	"seasonuuid" : "",
	"seriesuuid" : "",
	"sy" : "Sorted Food makes ultimate homemade nachos with smokey poached chicken.",
	"t" : "Ultimate Nachos",
	"uuid" : "Episode3978557804001120112"
}