{
	"childnodes" : 
	[
		{
			"imageUri" : "https://brightcove.hs.llnwd.net/v1/unsecured/media/3965454539001/201504/1329/3965454539001_4159375003001_8.jpg?pubId=3965454539001",
			"nodetype" : "PROGRAMME",
			"programmeid" : "Episode4110119562001110732",
			"sy" : "A combination market and restaurant in the International District, Ping’s serves some of the best dumplings in Seattle. The soup dumplings and pork and chive dumplings are standouts, but do yourself a favor and take the proprietress’ advice.",
			"t" : "9. Ping's Dumpling House"
		},
		{
			"imageUri" : "https://brightcove.hs.llnwd.net/v1/unsecured/media/3965454539001/201504/1329/3965454539001_4159374987001_6.jpg?pubId=3965454539001",
			"nodetype" : "PROGRAMME",
			"programmeid" : "Episode4110117748001110734",
			"sy" : "King Noodle’s congee — a type of rice porridge — makes the ultimate cold weather comfort food. Order some Chinese donuts for dipping if you really want to treat yourself.",
			"t" : "7. King Noodle"
		},
		{
			"imageUri" : "https://brightcove.hs.llnwd.net/v1/unsecured/media/3965454539001/201504/1945/3965454539001_4159374592001_7.jpg?pubId=3965454539001",
			"nodetype" : "PROGRAMME",
			"programmeid" : "Episode4110119561001110735",
			"sy" : "The beef brisket wonton noodle bowl, Chinese broccoli and Chinese donuts are must-order items at Mike’s Noodle House. It’s always packed, so allow time to park and wait for a table, and bring cash because they don’t take credit cards.",
			"t" : "8. Mike's Noodle House"
		},
		{
			"imageUri" : "https://brightcove.hs.llnwd.net/v1/unsecured/media/3965454539001/201504/3967/3965454539001_4159374977001_4.jpg?pubId=3965454539001",
			"nodetype" : "PROGRAMME",
			"programmeid" : "Episode4110119559001110736",
			"sy" : "Morning, noon or night, Honey Court serves up great seafood, dim sum and more. Pork and shrimp wonton soup makes a delicious late-night snack.",
			"t" : "5. Honey Court Seafood Restaurant"
		},
		{
			"imageUri" : "https://brightcove.hs.llnwd.net/v1/unsecured/media/3965454539001/201504/3671/3965454539001_4159357846001_5.jpg?pubId=3965454539001",
			"nodetype" : "PROGRAMME",
			"programmeid" : "Episode4110119560001110737",
			"sy" : "Hue Ky Mi Gia cooks great rice noodle dishes in the International District. They’re all about options here: all noodles can be ordered either dry or as a soup, and the pan-fried chicken wings are amazing, too.",
			"t" : "6. Hue Ky Mi Gia"
		},
		{
			"imageUri" : "https://brightcove.hs.llnwd.net/v1/unsecured/media/3965454539001/201504/2295/3965454539001_4159174942001_1.jpg?pubId=3965454539001",
			"nodetype" : "PROGRAMME",
			"programmeid" : "Episode4110119558001110738",
			"sy" : "There’s nothing like a steaming bowl of pho to warm and fill your belly on a cold day, and Green Leaf’s other dishes — like the omelet with pan-fried tofu — are delicious and hearty as well.",
			"t" : "2. Green Leaf Vietnamese Restaurant"
		},
		{
			"imageUri" : "https://brightcove.hs.llnwd.net/v1/unsecured/media/3965454539001/201504/1561/3965454539001_4159357836001_3.jpg?pubId=3965454539001",
			"nodetype" : "PROGRAMME",
			"programmeid" : "Episode4110114233001110739",
			"sy" : "Gourmet Noodle Bowl serves up hearty portions of its noodles, soups and dumplings, so be prepared to share. Start off with flavorful appetizers like the Taiwanese pork bun with peanut topping and Shanghai-style steamed dumplings.",
			"t" : "4. Gourmet Noodle Bowl"
		},
		{
			"imageUri" : "https://brightcove.hs.llnwd.net/v1/unsecured/media/3965454539001/201504/1967/3965454539001_4159374963001_1-1.jpg?pubId=3965454539001",
			"nodetype" : "PROGRAMME",
			"programmeid" : "Episode4110114232001110740",
			"sy" : "There’s always a huge line for the banh mi at Saigon Deli, and for good reason. Double ham, barbecue ham, spring roll –  it’s all incredible. Food is take-away only, so settle in at a nearby park to enjoy your sandwiches.",
			"t" : "1. Saigon Deli"
		}
	],
	"imageUri" : "https://images.contentful.com/za8hb1uldivj/59iZEQJ8aIs6UuOsa646qw/8a687ea7c001d45baa85f0dab06e2450/connected-devices-thumbnail-seattle-best-international-district-restaurants.png",
	"nodeid" : "Series140742",
	"nodetype" : "MENU",
	"t" : "Exploring the International District"
}